aws_elemental_python_client/__init__.py
aws_elemental_python_client/client.py
aws_elemental_python_client-1.0.0.dist-info/LICENSE
aws_elemental_python_client-1.0.0.dist-info/METADATA
aws_elemental_python_client-1.0.0.dist-info/WHEEL
aws_elemental_python_client-1.0.0.dist-info/top_level.txt
aws_elemental_python_client-1.0.0.dist-info/RECORD
