Metadata-Version: 2.1
Name: aws-elemental-python-client
Version: 1.0.0
Summary: Python Client for manage AWS Elemental Appliances (Delta, Live, Conductor)
Home-page: https://github.com/juanaugusto/aws-elemental-python-client.git
Author: Juan Augusto Santos de Paula
Author-email: jotaugusto93@gmail.com
License: UNKNOWN
Platform: UNKNOWN
Classifier: Programming Language :: Python :: 3
Classifier: License :: OSI Approved :: MIT License
Classifier: Operating System :: OS Independent
Requires-Python: >=3.8
Requires-Dist: requests (==2.24.0)
Requires-Dist: xmltodict (==0.12.0)
Requires-Dist: twine (==3.2.0)
